[
    {
        "name": "Deanne",
        "type": "minion",
        "mana": 2,
        "damage": 9,
        "health": 5
    },
    {
        "name": "Conley",
        "type": "minion",
        "mana": 5,
        "damage": 4,
        "health": 9
    },
    {
        "name": "Lillian",
        "type": "minion",
        "mana": 7,
        "damage": 8,
        "health": 6
    },
    {
        "name": "Bruce",
        "type": "minion",
        "mana": 8,
        "damage": 2,
        "health": 6
    },
    {
        "name": "Carroll",
        "type": "minion",
        "mana": 1,
        "damage": 5,
        "health": 4
    },
    {
        "name": "Sykes",
        "type": "minion",
        "mana": 1,
        "damage": 5,
        "health": 1
    },
    {
        "name": "Katrina",
        "type": "minion",
        "mana": 4,
        "damage": 5,
        "health": 8
    },
    {
        "name": "Juliana",
        "type": "minion",
        "mana": 3,
        "damage": 3,
        "health": 8
    },
    {
        "name": "Love",
        "type": "minion",
        "mana": 2,
        "damage": 4,
        "health": 1
    },
    {
        "name": "Savannah",
        "type": "minion",
        "mana": 7,
        "damage": 8,
        "health": 9
    },
    {
        "name": "Rosa",
        "type": "minion",
        "mana": 8,
        "damage": 1,
        "health": 10
    },
    {
        "name": "Aisha",
        "type": "minion",
        "mana": 10,
        "damage": 5,
        "health": 1
    },
    {
        "name": "Marshall",
        "type": "minion",
        "mana": 6,
        "damage": 2,
        "health": 6
    },
    {
        "name": "Jeannie",
        "type": "minion",
        "mana": 2,
        "damage": 4,
        "health": 10
    },
    {
        "name": "Lana",
        "type": "minion",
        "mana": 3,
        "damage": 6,
        "health": 3
    },
    {
        "name": "Robinson",
        "type": "minion",
        "mana": 10,
        "damage": 4,
        "health": 6
    },
    {
        "name": "Sabrina",
        "type": "minion",
        "mana": 4,
        "damage": 8,
        "health": 8
    },
    {
        "name": "Sara",
        "type": "minion",
        "mana": 7,
        "damage": 5,
        "health": 9
    },
    {
        "name": "Leticia",
        "type": "minion",
        "mana": 8,
        "damage": 8,
        "health": 2
    },
    {
        "name": "Cathryn",
        "type": "minion",
        "mana": 1,
        "damage": 2,
        "health": 7
    },
    {
        "name": "Nannie",
        "type": "minion",
        "mana": 10,
        "damage": 3,
        "health": 1
    },
    {
        "name": "Garrett",
        "type": "minion",
        "mana": 7,
        "damage": 9,
        "health": 1
    },
    {
        "name": "Frost",
        "type": "minion",
        "mana": 2,
        "damage": 4,
        "health": 7
    },
    {
        "name": "Cortez",
        "type": "minion",
        "mana": 2,
        "damage": 1,
        "health": 2
    },
    {
        "name": "Ochoa",
        "type": "minion",
        "mana": 2,
        "damage": 6,
        "health": 10
    },
    {
        "name": "Sandy",
        "type": "minion",
        "mana": 7,
        "damage": 7,
        "health": 9
    },
    {
        "name": "Pearlie",
        "type": "minion",
        "mana": 8,
        "damage": 4,
        "health": 9
    },
    {
        "name": "Tami",
        "type": "minion",
        "mana": 7,
        "damage": 8,
        "health": 4
    },
    {
        "name": "Katharine",
        "type": "minion",
        "mana": 10,
        "damage": 5,
        "health": 8
    },
    {
        "name": "Margie",
        "type": "minion",
        "mana": 2,
        "damage": 1,
        "health": 5
    },
    {
        "name": "Emilia",
        "type": "minion",
        "mana": 10,
        "damage": 6,
        "health": 1
    },
    {
        "name": "Dixon",
        "type": "minion",
        "mana": 9,
        "damage": 10,
        "health": 9
    },
    {
        "name": "Anderson",
        "type": "minion",
        "mana": 9,
        "damage": 2,
        "health": 8
    },
    {
        "name": "Perry",
        "type": "minion",
        "mana": 5,
        "damage": 10,
        "health": 8
    },
    {
        "name": "Fran",
        "type": "minion",
        "mana": 9,
        "damage": 1,
        "health": 7
    },
    {
        "name": "Ora",
        "type": "minion",
        "mana": 1,
        "damage": 7,
        "health": 3
    },
    {
        "name": "Bernadette",
        "type": "minion",
        "mana": 4,
        "damage": 2,
        "health": 10
    },
    {
        "name": "Amber",
        "type": "minion",
        "mana": 6,
        "damage": 10,
        "health": 9
    },
    {
        "name": "Lane",
        "type": "minion",
        "mana": 2,
        "damage": 4,
        "health": 9
    },
    {
        "name": "Preston",
        "type": "minion",
        "mana": 10,
        "damage": 5,
        "health": 1
    },
    {
        "name": "Wendi",
        "type": "minion",
        "mana": 6,
        "damage": 1,
        "health": 7
    },
    {
        "name": "Porter",
        "type": "minion",
        "mana": 3,
        "damage": 1,
        "health": 7
    },
    {
        "name": "Doyle",
        "type": "minion",
        "mana": 10,
        "damage": 5,
        "health": 10
    },
    {
        "name": "Araceli",
        "type": "minion",
        "mana": 9,
        "damage": 6,
        "health": 7
    },
    {
        "name": "Brandi",
        "type": "minion",
        "mana": 10,
        "damage": 2,
        "health": 8
    },
    {
        "name": "Rivera",
        "type": "minion",
        "mana": 3,
        "damage": 1,
        "health": 4
    },
    {
        "name": "Albert",
        "type": "minion",
        "mana": 8,
        "damage": 7,
        "health": 7
    },
    {
        "name": "Lupe",
        "type": "minion",
        "mana": 10,
        "damage": 4,
        "health": 4
    },
    {
        "name": "Yesenia",
        "type": "minion",
        "mana": 2,
        "damage": 4,
        "health": 6
    },
    {
        "name": "Blanche",
        "type": "minion",
        "mana": 9,
        "damage": 7,
        "health": 7
    },
    {
        "name": "Edna",
        "type": "minion",
        "mana": 4,
        "damage": 4,
        "health": 4
    },
    {
        "name": "Flora",
        "type": "minion",
        "mana": 4,
        "damage": 7,
        "health": 9
    },
    {
        "name": "Mathis",
        "type": "minion",
        "mana": 10,
        "damage": 10,
        "health": 6
    },
    {
        "name": "Lorie",
        "type": "minion",
        "mana": 4,
        "damage": 9,
        "health": 10
    },
    {
        "name": "Alyce",
        "type": "minion",
        "mana": 1,
        "damage": 7,
        "health": 8
    },
    {
        "name": "Harmon",
        "type": "minion",
        "mana": 9,
        "damage": 10,
        "health": 8
    },
    {
        "name": "Dolly",
        "type": "minion",
        "mana": 9,
        "damage": 1,
        "health": 9
    },
    {
        "name": "Adriana",
        "type": "minion",
        "mana": 7,
        "damage": 1,
        "health": 6
    },
    {
        "name": "Spears",
        "type": "minion",
        "mana": 8,
        "damage": 6,
        "health": 3
    },
    {
        "name": "Jan",
        "type": "minion",
        "mana": 4,
        "damage": 1,
        "health": 2
    },
    {
        "name": "Lang",
        "type": "minion",
        "mana": 10,
        "damage": 1,
        "health": 2
    },
    {
        "name": "Dudley",
        "type": "minion",
        "mana": 2,
        "damage": 8,
        "health": 5
    },
    {
        "name": "Moses",
        "type": "minion",
        "mana": 2,
        "damage": 5,
        "health": 4
    },
    {
        "name": "Stevens",
        "type": "minion",
        "mana": 7,
        "damage": 8,
        "health": 4
    },
    {
        "name": "Romero",
        "type": "minion",
        "mana": 8,
        "damage": 9,
        "health": 2
    },
    {
        "name": "Claudia",
        "type": "minion",
        "mana": 10,
        "damage": 1,
        "health": 9
    },
    {
        "name": "Hoover",
        "type": "minion",
        "mana": 7,
        "damage": 4,
        "health": 3
    },
    {
        "name": "Adeline",
        "type": "minion",
        "mana": 8,
        "damage": 6,
        "health": 5
    },
    {
        "name": "Rojas",
        "type": "minion",
        "mana": 1,
        "damage": 10,
        "health": 2
    },
    {
        "name": "Mallory",
        "type": "minion",
        "mana": 3,
        "damage": 8,
        "health": 10
    },
    {
        "name": "Jeannette",
        "type": "minion",
        "mana": 9,
        "damage": 10,
        "health": 10
    },
    {
        "name": "Burch",
        "type": "minion",
        "mana": 9,
        "damage": 4,
        "health": 6
    },
    {
        "name": "Ines",
        "type": "minion",
        "mana": 2,
        "damage": 7,
        "health": 2
    },
    {
        "name": "Summer",
        "type": "minion",
        "mana": 8,
        "damage": 9,
        "health": 6
    },
    {
        "name": "Bonner",
        "type": "minion",
        "mana": 1,
        "damage": 7,
        "health": 2
    },
    {
        "name": "Nanette",
        "type": "minion",
        "mana": 8,
        "damage": 2,
        "health": 1
    },
    {
        "name": "Howell",
        "type": "minion",
        "mana": 8,
        "damage": 1,
        "health": 8
    },
    {
        "name": "Giles",
        "type": "minion",
        "mana": 2,
        "damage": 8,
        "health": 4
    },
    {
        "name": "Hall",
        "type": "minion",
        "mana": 3,
        "damage": 1,
        "health": 4
    },
    {
        "name": "Leon",
        "type": "minion",
        "mana": 9,
        "damage": 5,
        "health": 5
    },
    {
        "name": "Amie",
        "type": "minion",
        "mana": 7,
        "damage": 8,
        "health": 6
    },
    {
        "name": "Meyer",
        "type": "minion",
        "mana": 3,
        "damage": 8,
        "health": 8
    },
    {
        "name": "Meredith",
        "type": "minion",
        "mana": 9,
        "damage": 5,
        "health": 2
    },
    {
        "name": "Kelli",
        "type": "minion",
        "mana": 4,
        "damage": 1,
        "health": 8
    },
    {
        "name": "Fuller",
        "type": "minion",
        "mana": 6,
        "damage": 10,
        "health": 3
    },
    {
        "name": "Toni",
        "type": "minion",
        "mana": 6,
        "damage": 9,
        "health": 10
    },
    {
        "name": "James",
        "type": "minion",
        "mana": 1,
        "damage": 9,
        "health": 3
    },
    {
        "name": "Mara",
        "type": "minion",
        "mana": 2,
        "damage": 3,
        "health": 3
    },
    {
        "name": "Santiago",
        "type": "minion",
        "mana": 7,
        "damage": 4,
        "health": 10
    },
    {
        "name": "Hodge",
        "type": "minion",
        "mana": 7,
        "damage": 3,
        "health": 1
    },
    {
        "name": "Berg",
        "type": "minion",
        "mana": 2,
        "damage": 4,
        "health": 3
    },
    {
        "name": "Edwina",
        "type": "minion",
        "mana": 8,
        "damage": 7,
        "health": 1
    },
    {
        "name": "Freda",
        "type": "minion",
        "mana": 3,
        "damage": 8,
        "health": 6
    },
    {
        "name": "Eve",
        "type": "minion",
        "mana": 1,
        "damage": 10,
        "health": 4
    },
    {
        "name": "Simpson",
        "type": "minion",
        "mana": 3,
        "damage": 9,
        "health": 6
    },
    {
        "name": "Celina",
        "type": "minion",
        "mana": 2,
        "damage": 2,
        "health": 1
    },
    {
        "name": "Oneal",
        "type": "minion",
        "mana": 2,
        "damage": 4,
        "health": 4
    },
    {
        "name": "Rosemary",
        "type": "minion",
        "mana": 4,
        "damage": 9,
        "health": 1
    },
    {
        "name": "Berger",
        "type": "minion",
        "mana": 3,
        "damage": 5,
        "health": 8
    },
    {
        "name": "Hopkins",
        "type": "minion",
        "mana": 6,
        "damage": 10,
        "health": 5
    },
    {
        "name": "Tania",
        "type": "minion",
        "mana": 7,
        "damage": 9,
        "health": 7
    },
    {
        "name": "Harriet",
        "type": "minion",
        "mana": 3,
        "damage": 8,
        "health": 7
    },
    {
        "name": "Morse",
        "type": "minion",
        "mana": 10,
        "damage": 5,
        "health": 9
    },
    {
        "name": "Collins",
        "type": "minion",
        "mana": 9,
        "damage": 3,
        "health": 10
    },
    {
        "name": "Terry",
        "type": "minion",
        "mana": 10,
        "damage": 10,
        "health": 9
    },
    {
        "name": "Juliette",
        "type": "minion",
        "mana": 10,
        "damage": 2,
        "health": 10
    },
    {
        "name": "Camille",
        "type": "minion",
        "mana": 10,
        "damage": 1,
        "health": 7
    },
    {
        "name": "Gomez",
        "type": "minion",
        "mana": 1,
        "damage": 5,
        "health": 3
    },
    {
        "name": "Clarice",
        "type": "minion",
        "mana": 2,
        "damage": 4,
        "health": 7
    },
    {
        "name": "Levine",
        "type": "minion",
        "mana": 2,
        "damage": 3,
        "health": 6
    },
    {
        "name": "Marian",
        "type": "minion",
        "mana": 6,
        "damage": 6,
        "health": 8
    },
    {
        "name": "Garrison",
        "type": "minion",
        "mana": 2,
        "damage": 2,
        "health": 2
    },
    {
        "name": "Fox",
        "type": "minion",
        "mana": 4,
        "damage": 6,
        "health": 4
    },
    {
        "name": "Mendoza",
        "type": "minion",
        "mana": 4,
        "damage": 6,
        "health": 8
    },
    {
        "name": "Fern",
        "type": "minion",
        "mana": 7,
        "damage": 1,
        "health": 6
    },
    {
        "name": "Alford",
        "type": "minion",
        "mana": 6,
        "damage": 8,
        "health": 3
    },
    {
        "name": "Shana",
        "type": "minion",
        "mana": 5,
        "damage": 7,
        "health": 2
    },
    {
        "name": "Angel",
        "type": "minion",
        "mana": 9,
        "damage": 10,
        "health": 7
    },
    {
        "name": "Gould",
        "type": "minion",
        "mana": 9,
        "damage": 4,
        "health": 6
    },
    {
        "name": "Veronica",
        "type": "minion",
        "mana": 7,
        "damage": 7,
        "health": 10
    },
    {
        "type": "minion",
        "name": "Crazy Shirtless Dude",
        "mana": 1,
        "damage": 1,
        "health": 2,
        "ability": {
            "type": "gain_damage",
            "params": { "amount": 1 },
            "trigger": "turn_started"
        }
    },
    {
        "type": "minion",
        "name": "Black Magician of Doom",
        "mana": 2,
        "damage": 5,
        "health": 2,
        "ability": {
            "type": "draw_card",
            "params": { "amount": 1 },
            "trigger": "minion_destroyed",
            "condition": "allied"
        }
    }
]
